{
  "model": {
    "name": "LegacyTabulation",
    "package": "org.ums.result.legacy",
    "fields": [
      {
        "id": {
          "type": "Long",
          "idType": true
        }
      },
      {
        "gpa": "Double"
      },
      {
        "cgpa": "Double"
      },
      {
        "comment": "String"
      },
      {
        "year" : "Integer"
      },
      {
        "academicSemester": "Integer"
      },
      {
        "semester": {
          "type": "Ref",
          "reference": {
            "name": "Semester",
            "package": "org.ums.domain.model.immutable",
            "id": {
              "type": "Integer"
            },
            "manager": {
              "name": "SemesterManager",
              "package": "org.ums.manager"
            }
          }
        }
      },
      {
        "student": {
          "type": "Ref",
          "reference": {
            "name": "Student",
            "package": "org.ums.domain.model.immutable",
            "id": {
              "type": "String"
            },
            "manager": {
              "name": "StudentManager",
              "package": "org.ums.manager"
            }
          }
        }
      }
    ]
  }
}
